AutoThemeGenerator/AutoThemeGenerator.py
AutoThemeGenerator/__init__.py
AutoThemeGenerator-0.2.1.dist-info/LICENSE.txt
AutoThemeGenerator-0.2.1.dist-info/METADATA
AutoThemeGenerator-0.2.1.dist-info/WHEEL
AutoThemeGenerator-0.2.1.dist-info/top_level.txt
AutoThemeGenerator-0.2.1.dist-info/RECORD
