Metadata-Version: 2.1
Name: AutoThemeGenerator
Version: 0.2.1
Summary: Performing thematic analysis with OpenAI's GPT-4 models
Author: Charles Alba
Author-email: alba@wustl.edu
Keywords: GPT models,Thematic analysis,OpenAI,Qualitiative studies,transcripts,interviews
Classifier: Development Status :: 1 - Planning
Classifier: Intended Audience :: Education
Classifier: Intended Audience :: Science/Research
Classifier: Programming Language :: Python :: 3
Classifier: Operating System :: Unix
Classifier: Operating System :: MacOS :: MacOS X
Classifier: Operating System :: Microsoft :: Windows
License-File: LICENSE.txt
Requires-Dist: textract
Requires-Dist: openai
Requires-Dist: nltk ==3.8.1
Requires-Dist: python-docx
Requires-Dist: docx
Requires-Dist: tqdm
